filerohr/__init__.py
filerohr/__main__.py
filerohr/config.py
filerohr/env.py
filerohr/pipeline/__init__.py
filerohr/pipeline/events.py
filerohr/pipeline/models.py
filerohr/pipeline/types.py
filerohr/tasks/__init__.py
filerohr/tasks/av.py
filerohr/tasks/av_utils.py
filerohr/tasks/generic.py
filerohr/tasks/remote.py
filerohr/tasks/remote_utils.py
filerohr/utils/__init__.py
filerohr/utils/generic.py
filerohr/utils/http.py
filerohr/utils/io.py
filerohr/utils/time.py
filerohr/utils/yaml.py
filerohr-0.1.0.dist-info/METADATA
filerohr-0.1.0.dist-info/WHEEL
filerohr-0.1.0.dist-info/licenses/LICENSE
filerohr-0.1.0.dist-info/RECORD
