Metadata-Version: 2.4
Name: filerohr
Version: 0.1.0
Summary: A pipeline-based file processing library.
Project-URL: repository, https://codeberg.org/kmohrf/filerohr
Project-URL: documentation, https://python-poetry.org/docs/
Project-URL: Bug Tracker, https://codeberg.org/kmohrf/filerohr/issues
Author-email: Konrad Mohrfeldt <km@roko.li>
License-Expression: AGPL-3.0-or-later
License-File: LICENSE
Requires-Python: >=3.13
Requires-Dist: aiofiles>=25.1.0
Requires-Dist: blinker>=1.9.0
Requires-Dist: httpx>=0.28.1
Requires-Dist: pebble>=5.1.3
Requires-Dist: pydantic>=2.12.4
Requires-Dist: pyyaml>=6.0.3
